setup.py
TODO_Tools.egg-info/PKG-INFO
TODO_Tools.egg-info/SOURCES.txt
TODO_Tools.egg-info/dependency_links.txt
TODO_Tools.egg-info/requires.txt
TODO_Tools.egg-info/top_level.txt
bin/todo
todo_tools/__init__.py
todo_tools/todo_tools.py
todo_tools.egg-info/SOURCES.txt