Metadata-Version: 1.0
Name: TODO-Tools
Version: 1.0.5
Summary: Tools to manage git TODOs
Home-page: UNKNOWN
Author: UNKNOWN
Author-email: UNKNOWN
License: MIT
Platform: UNKNOWN
